invenio_records_draft/__init__.py
invenio_records_draft/api.py
invenio_records_draft/cli.py
invenio_records_draft/endpoints.py
invenio_records_draft/ext.py
invenio_records_draft/proxies.py
invenio_records_draft/record.py
invenio_records_draft/signals.py
invenio_records_draft/utils.py
invenio_records_draft/version.py
invenio_records_draft/mappings/v6/draft.json
invenio_records_draft/mappings/v7/draft.json
invenio_records_draft/marshmallow/__init__.py
invenio_records_draft/marshmallow/draft.py
invenio_records_draft/views/__init__.py
invenio_records_draft/views/edit.py
invenio_records_draft/views/publish.py
invenio_records_draft/views/unpublish.py
oarepo_invenio_records_draft-4.1.0.dist-info/LICENSE
oarepo_invenio_records_draft-4.1.0.dist-info/METADATA
oarepo_invenio_records_draft-4.1.0.dist-info/WHEEL
oarepo_invenio_records_draft-4.1.0.dist-info/entry_points.txt
oarepo_invenio_records_draft-4.1.0.dist-info/top_level.txt
oarepo_invenio_records_draft-4.1.0.dist-info/RECORD
